my_simple_package/__init__.py
harsh-0.1.1.dist-info/METADATA
harsh-0.1.1.dist-info/WHEEL
harsh-0.1.1.dist-info/license
harsh-0.1.1.dist-info/top_level.txt
harsh-0.1.1.dist-info/RECORD
