Metadata-Version: 2.1
Name: harsh
Version: 0.1.1
Summary: Text Manipulation and Analysis Package
Home-page: https://github.com/yourusername/harsh
Author: Jayesh Jain
Author-email: your.email@example.com
Classifier: Programming Language :: Python :: 3
Classifier: License :: OSI Approved :: MIT License
Classifier: Operating System :: OS Independent
Requires-Python: >=3.6
License-File: license
